LICENSE
MANIFEST.in
README.rst
setup.py
firstapp/__init__.py
firstapp/__main__.py
firstapp/firstapp.py
firstapp/helpers.py
pthapa_first_app.egg-info/PKG-INFO
pthapa_first_app.egg-info/SOURCES.txt
pthapa_first_app.egg-info/dependency_links.txt
pthapa_first_app.egg-info/entry_points.txt
pthapa_first_app.egg-info/top_level.txt