Metadata-Version: 1.0
Name: pthapa-first-app
Version: 1.20
Summary: Python command line application bare bones template.
Home-page: UNKNOWN
Author: Parmeshwor Thapa
Author-email: thapa.parmeshwor@gmail.com
License: UNKNOWN
Platform: UNKNOWN
